pyopendart/__init__.py
pyopendart/api/__init__.py
pyopendart/api/base.py
pyopendart/api/const.py
pyopendart/api/dataframe/__init__.py
pyopendart/api/dataframe/business_report.py
pyopendart/api/dataframe/filling.py
pyopendart/api/dataframe/financial_statement.py
pyopendart/api/dataframe/shareholders_report.py
pyopendart/api/dataframe/utils.py
pyopendart/api/dict/__init__.py
pyopendart/api/dict/business_report.py
pyopendart/api/dict/filling.py
pyopendart/api/dict/financial_statement.py
pyopendart/api/dict/shareholders_report.py
pyopendart/api/http/__init__.py
pyopendart/api/http/httpx.py
pyopendart/api/http/requests.py
pyopendart/descriptions.py
pyopendart/enums.py
pyopendart/exceptions.py
pyopendart/utils.py
pyopendart-0.3.0.dist-info/LICENSE
pyopendart-0.3.0.dist-info/WHEEL
pyopendart-0.3.0.dist-info/METADATA
pyopendart-0.3.0.dist-info/RECORD
