Metadata-Version: 2.1
Name: pyopendart
Version: 0.3.0
Summary: 전자공시시스템 DART 파이썬 API (for Humans)
Home-page: https://github.com/NovemberOscar/pyOPENDART
License: MIT
Keywords: data,market,stock,korea,investment,kospi,kosdaq
Author: Seonghyeon Kim
Author-email: self@seonghyeon.dev
Requires-Python: >=3.7.1,<4.0.0
Classifier: Development Status :: 3 - Alpha
Classifier: License :: OSI Approved :: MIT License
Classifier: Natural Language :: Korean
Classifier: Programming Language :: Python :: 3
Classifier: Programming Language :: Python :: 3.7
Classifier: Programming Language :: Python :: 3.8
Classifier: Programming Language :: Python :: 3.9
Classifier: Topic :: Office/Business :: Financial
Classifier: Topic :: Office/Business :: Financial :: Accounting
Classifier: Topic :: Office/Business :: Financial :: Investment
Provides-Extra: httpx
Requires-Dist: furl (>=2.1.0,<3.0.0)
Requires-Dist: httpx (>=0.16.1,<0.17.0); extra == "httpx"
Requires-Dist: pandas (>=1.2.1,<2.0.0)
Requires-Dist: python-dateutil (>=2.8.1,<3.0.0)
Requires-Dist: requests (>=2.25.1,<3.0.0)
Project-URL: Repository, https://github.com/NovemberOscar/pyOPENDART
